kanjize/__about__.py
kanjize/__init__.py
kanjize/kanjize.py
kanjize/py.typed
kanjize-1.6.1.dist-info/METADATA
kanjize-1.6.1.dist-info/WHEEL
kanjize-1.6.1.dist-info/licenses/LICENSE
kanjize-1.6.1.dist-info/RECORD
