Metadata-Version: 2.4
Name: kanjize
Version: 1.6.1
Summary: Easy converter between Kanji-Number and Integer
Project-URL: Homepage, https://github.com/nagataaaas/Kanjize
Project-URL: Documentation, https://github.com/nagataaaas/Kanjize/blob/master/README.md
Project-URL: Repository, https://github.com/nagataaaas/Kanjize.git
Project-URL: Issues, https://github.com/nagataaaas/Kanjize/issues
Project-URL: Changelog, https://github.com/nagataaaas/Kanjize/blob/master/CHANGELOG.md
Author-email: nagataaaas <nagata@nagata.pro>
License-File: LICENSE
Keywords: converter,integer,japanese,kanji,number
Classifier: Development Status :: 5 - Production/Stable
Classifier: Environment :: Other Environment
Classifier: Intended Audience :: Developers
Classifier: License :: OSI Approved :: MIT License
Classifier: Operating System :: OS Independent
Classifier: Programming Language :: Python
Classifier: Programming Language :: Python :: 3
Classifier: Topic :: Software Development :: Libraries :: Python Modules
Requires-Python: >=3.8
